mcp_digital_ocean_billing/__init__.py
mcp_digital_ocean_billing/server.py
mcp_digital_ocean_billing-0.0.3.dist-info/METADATA
mcp_digital_ocean_billing-0.0.3.dist-info/WHEEL
mcp_digital_ocean_billing-0.0.3.dist-info/entry_points.txt
mcp_digital_ocean_billing-0.0.3.dist-info/top_level.txt
mcp_digital_ocean_billing-0.0.3.dist-info/RECORD
