Metadata-Version: 2.4
Name: mcp-digital_ocean_billing
Version: 0.0.3
Summary: MCP server for Digital Ocean Billing integration
Project-URL: Homepage, https://github.com/curious-pm/mcp-digital_ocean_billing
Project-URL: Bug Tracker, https://github.com/curious-pm/mcp-digital_ocean_billing/issues
Requires-Python: >=3.10
Requires-Dist: mcp[cli]>=1.6.0
Requires-Dist: httpx>=0.24.0
